pyum/__init__.py
pyum/HTTPClient.py
pyum/Repo.py
pyum/rpm.py
pyum/repometadata/__init__.py
pyum/repometadata/BaseData.py
pyum/repometadata/group.py
pyum/repometadata/primary.py
pyum-0.1.1.dist-info/DESCRIPTION.rst
pyum-0.1.1.dist-info/METADATA
pyum-0.1.1.dist-info/metadata.json
pyum-0.1.1.dist-info/RECORD
pyum-0.1.1.dist-info/top_level.txt
pyum-0.1.1.dist-info/WHEEL
