Metadata-Version: 2.0
Name: pyum
Version: 0.1.1
Summary: A library for reading yum repositories and rpm metadata
Home-page: https://github.com/drewsonne/pyum
Author: Drew J. Sonne
Author-email: drew.sonne@gmail.com
License: UNKNOWN
Platform: UNKNOWN
